campdown/__init__.py
campdown/album.py
campdown/discography.py
campdown/helpers.py
campdown/track.py
campdown-1.49.dist-info/LICENSE
campdown-1.49.dist-info/METADATA
campdown-1.49.dist-info/WHEEL
campdown-1.49.dist-info/entry_points.txt
campdown-1.49.dist-info/top_level.txt
campdown-1.49.dist-info/RECORD
