Metadata-Version: 2.1
Name: campdown
Version: 1.49
Summary: Bandcamp track and album downloader
Home-page: https://github.com/catlinman/campdown/
Author: Catlinman
Author-email: contact@catlinman.com
License: MIT
Keywords: bandcamp,downloader,utility
Platform: UNKNOWN
Classifier: Environment :: Console
Classifier: Intended Audience :: Developers
Classifier: Intended Audience :: End Users/Desktop
Classifier: License :: OSI Approved :: MIT License
Classifier: Programming Language :: Python :: 3.4
Classifier: Programming Language :: Python :: 3.5
Classifier: Programming Language :: Python :: 3.6
Classifier: Programming Language :: Python :: 3 :: Only
Classifier: Topic :: Multimedia :: Sound/Audio
Classifier: Topic :: Utilities
Requires-Dist: requests (>=2.22.0)
Requires-Dist: mutagen (>=1.42.0)
Requires-Dist: docopt (>=0.6.2)
